lenddo_api_client/__init__.py
lenddo_api_client/__version__.py
lenddo_api_client/base.py
lenddo_api_client/compat.py
lenddo_api_client/errors.py
lenddo-1.2.0.dist-info/LICENSE
lenddo-1.2.0.dist-info/METADATA
lenddo-1.2.0.dist-info/WHEEL
lenddo-1.2.0.dist-info/top_level.txt
lenddo-1.2.0.dist-info/RECORD
