Metadata-Version: 2.1
Name: lenddo
Version: 1.2.0
Summary: Python library for integrating Lenddo Services. https://www.lenddo.com
Home-page: https://github.com/Lenddo/python-lenddo
Author: Lenddo
Author-email: techbilling@lenddo.com
License: UNKNOWN
Keywords: lenddo api client
Platform: UNKNOWN
Classifier: Development Status :: 4 - Beta
Classifier: Intended Audience :: Developers
Classifier: License :: OSI Approved :: MIT License
Classifier: Programming Language :: Python :: 2.7
Classifier: Topic :: Software Development :: Libraries
